[
  {
    "ContainingType": "API.Controllers.AmenityController",
    "Method": "AddAmenitySystem",
    "RelativePath": "api/Amenity/add-system-amenity",
    "HttpMethod": "POST",
    "IsController": true,
    "Order": 0,
    "Parameters": [
      {
        "Name": "request",
        "Type": "BusinessObject.DTO.AddSystemAmenityRequest",
        "IsRequired": true
      }
    ],
    "ReturnTypes": []
  },
  {
    "ContainingType": "API.Controllers.AmenityController",
    "Method": "GetAllSystemAmenity",
    "RelativePath": "api/Amenity/get-all-system-amenity",
    "HttpMethod": "GET",
    "IsController": true,
    "Order": 0,
    "Parameters": [],
    "ReturnTypes": []
  },
  {
    "ContainingType": "API.Controllers.AuthController",
    "Method": "AccessToken",
    "RelativePath": "api/Auth/access-token",
    "HttpMethod": "PUT",
    "IsController": true,
    "Order": 0,
    "Parameters": [
      {
        "Name": "command",
        "Type": "BusinessObject.DTO.AccessTokenDTO",
        "IsRequired": true
      }
    ],
    "ReturnTypes": []
  },
  {
    "ContainingType": "API.Controllers.AuthController",
    "Method": "Block",
    "RelativePath": "api/Auth/block",
    "HttpMethod": "PUT",
    "IsController": true,
    "Order": 0,
    "Parameters": [
      {
        "Name": "id",
        "Type": "System.Guid",
        "IsRequired": false
      }
    ],
    "ReturnTypes": []
  },
  {
    "ContainingType": "API.Controllers.AuthController",
    "Method": "ChangePassword",
    "RelativePath": "api/Auth/change-password",
    "HttpMethod": "PUT",
    "IsController": true,
    "Order": 0,
    "Parameters": [
      {
        "Name": "command",
        "Type": "BusinessObject.DTO.ChangePasswordDTO",
        "IsRequired": true
      }
    ],
    "ReturnTypes": []
  },
  {
    "ContainingType": "API.Controllers.AuthController",
    "Method": "ConfirmEmail",
    "RelativePath": "api/Auth/confirm-email",
    "HttpMethod": "GET",
    "IsController": true,
    "Order": 0,
    "Parameters": [
      {
        "Name": "userId",
        "Type": "System.Guid",
        "IsRequired": false
      },
      {
        "Name": "code",
        "Type": "System.String",
        "IsRequired": false
      }
    ],
    "ReturnTypes": []
  },
  {
    "ContainingType": "API.Controllers.AuthController",
    "Method": "ForgotPassword",
    "RelativePath": "api/Auth/forgot-password",
    "HttpMethod": "PUT",
    "IsController": true,
    "Order": 0,
    "Parameters": [
      {
        "Name": "command",
        "Type": "BusinessObject.DTO.ForgotPasswordDTO",
        "IsRequired": true
      }
    ],
    "ReturnTypes": []
  },
  {
    "ContainingType": "API.Controllers.AuthController",
    "Method": "Get",
    "RelativePath": "api/Auth/get-me",
    "HttpMethod": "GET",
    "IsController": true,
    "Order": 0,
    "Parameters": [
      {
        "Name": "X-User-Id",
        "Type": "System.Guid",
        "IsRequired": false
      }
    ],
    "ReturnTypes": []
  },
  {
    "ContainingType": "API.Controllers.AuthController",
    "Method": "Login",
    "RelativePath": "api/Auth/login",
    "HttpMethod": "POST",
    "IsController": true,
    "Order": 0,
    "Parameters": [
      {
        "Name": "command",
        "Type": "BusinessObject.DTO.LoginDTO",
        "IsRequired": true
      }
    ],
    "ReturnTypes": []
  },
  {
    "ContainingType": "API.Controllers.AuthController",
    "Method": "Register",
    "RelativePath": "api/Auth/register",
    "HttpMethod": "POST",
    "IsController": true,
    "Order": 0,
    "Parameters": [
      {
        "Name": "command",
        "Type": "BusinessObject.DTO.RegisterDTO",
        "IsRequired": true
      }
    ],
    "ReturnTypes": []
  },
  {
    "ContainingType": "API.Controllers.AuthController",
    "Method": "ReSendConfirmEmail",
    "RelativePath": "api/Auth/resend-confirm",
    "HttpMethod": "POST",
    "IsController": true,
    "Order": 0,
    "Parameters": [
      {
        "Name": "command",
        "Type": "BusinessObject.DTO.ResendConfirmEmailDTO",
        "IsRequired": true
      }
    ],
    "ReturnTypes": []
  },
  {
    "ContainingType": "API.Controllers.AuthController",
    "Method": "ResetPassword",
    "RelativePath": "api/Auth/reset-password",
    "HttpMethod": "PUT",
    "IsController": true,
    "Order": 0,
    "Parameters": [
      {
        "Name": "command",
        "Type": "BusinessObject.DTO.ResetPasswordDTO",
        "IsRequired": true
      }
    ],
    "ReturnTypes": []
  },
  {
    "ContainingType": "API.Controllers.AuthController",
    "Method": "UnBlock",
    "RelativePath": "api/Auth/unblock",
    "HttpMethod": "PUT",
    "IsController": true,
    "Order": 0,
    "Parameters": [
      {
        "Name": "id",
        "Type": "System.Guid",
        "IsRequired": false
      }
    ],
    "ReturnTypes": []
  },
  {
    "ContainingType": "RUNAHMS_API.Controllers.BookingController",
    "Method": "CancelBooking",
    "RelativePath": "api/Booking/cancel",
    "HttpMethod": "POST",
    "IsController": true,
    "Order": 0,
    "Parameters": [
      {
        "Name": "bookingId",
        "Type": "System.Guid",
        "IsRequired": false
      }
    ],
    "ReturnTypes": []
  },
  {
    "ContainingType": "RUNAHMS_API.Controllers.BookingController",
    "Method": "ConfirmBooking",
    "RelativePath": "api/Booking/confirm",
    "HttpMethod": "GET",
    "IsController": true,
    "Order": 0,
    "Parameters": [
      {
        "Name": "bookingId",
        "Type": "System.Guid",
        "IsRequired": false
      }
    ],
    "ReturnTypes": []
  },
  {
    "ContainingType": "RUNAHMS_API.Controllers.BookingController",
    "Method": "ConfirmBookingStatus",
    "RelativePath": "api/Booking/confirm-booking-status",
    "HttpMethod": "PUT",
    "IsController": true,
    "Order": 0,
    "Parameters": [
      {
        "Name": "bookingID",
        "Type": "System.Guid",
        "IsRequired": false
      }
    ],
    "ReturnTypes": []
  },
  {
    "ContainingType": "RUNAHMS_API.Controllers.BookingController",
    "Method": "ConfirmCancelBooking",
    "RelativePath": "api/Booking/confirm-cancel",
    "HttpMethod": "GET",
    "IsController": true,
    "Order": 0,
    "Parameters": [
      {
        "Name": "bookingId",
        "Type": "System.Guid",
        "IsRequired": false
      }
    ],
    "ReturnTypes": []
  },
  {
    "ContainingType": "RUNAHMS_API.Controllers.BookingController",
    "Method": "CreateBooking",
    "RelativePath": "api/Booking/create",
    "HttpMethod": "POST",
    "IsController": true,
    "Order": 0,
    "Parameters": [
      {
        "Name": "X-User-Id",
        "Type": "System.Guid",
        "IsRequired": false
      },
      {
        "Name": "bookingDTO",
        "Type": "BusinessObject.DTO.BookingDTO",
        "IsRequired": true
      }
    ],
    "ReturnTypes": []
  },
  {
    "ContainingType": "RUNAHMS_API.Controllers.BookingController",
    "Method": "GetBookingHistory",
    "RelativePath": "api/Booking/history",
    "HttpMethod": "GET",
    "IsController": true,
    "Order": 0,
    "Parameters": [
      {
        "Name": "X-User-Id",
        "Type": "System.Guid",
        "IsRequired": false
      }
    ],
    "ReturnTypes": []
  },
  {
    "ContainingType": "API.Controllers.CalendarController",
    "Method": "GetById",
    "RelativePath": "api/Calendar/{id}",
    "HttpMethod": "GET",
    "IsController": true,
    "Order": 0,
    "Parameters": [
      {
        "Name": "id",
        "Type": "System.Guid",
        "IsRequired": true
      }
    ],
    "ReturnTypes": []
  },
  {
    "ContainingType": "API.Controllers.CalendarController",
    "Method": "Update",
    "RelativePath": "api/Calendar/{id}",
    "HttpMethod": "PUT",
    "IsController": true,
    "Order": 0,
    "Parameters": [
      {
        "Name": "id",
        "Type": "System.Guid",
        "IsRequired": true
      },
      {
        "Name": "dto",
        "Type": "BusinessObject.DTO.CalendarDTO",
        "IsRequired": true
      }
    ],
    "ReturnTypes": []
  },
  {
    "ContainingType": "API.Controllers.CalendarController",
    "Method": "SoftDelete",
    "RelativePath": "api/Calendar/{id}",
    "HttpMethod": "DELETE",
    "IsController": true,
    "Order": 0,
    "Parameters": [
      {
        "Name": "id",
        "Type": "System.Guid",
        "IsRequired": true
      }
    ],
    "ReturnTypes": []
  },
  {
    "ContainingType": "API.Controllers.CalendarController",
    "Method": "GetByHomeStayId",
    "RelativePath": "api/Calendar/homestay/{homeStayId}",
    "HttpMethod": "GET",
    "IsController": true,
    "Order": 0,
    "Parameters": [
      {
        "Name": "homeStayId",
        "Type": "System.Guid",
        "IsRequired": true
      }
    ],
    "ReturnTypes": []
  },
  {
    "ContainingType": "API.Controllers.FacilityController",
    "Method": "AddFacility",
    "RelativePath": "api/Facility/add-facility",
    "HttpMethod": "POST",
    "IsController": true,
    "Order": 0,
    "Parameters": [
      {
        "Name": "request",
        "Type": "System.Collections.Generic.List\u00601[[BusinessObject.DTO.AddFacilityDTO, Bussiness Object, Version=1.0.0.0, Culture=neutral, PublicKeyToken=null]]",
        "IsRequired": true
      }
    ],
    "ReturnTypes": []
  },
  {
    "ContainingType": "API.Controllers.FacilityController",
    "Method": "DeleteFacility",
    "RelativePath": "api/Facility/delete-facility",
    "HttpMethod": "DELETE",
    "IsController": true,
    "Order": 0,
    "Parameters": [
      {
        "Name": "request",
        "Type": "BusinessObject.DTO.DeleteListDTO",
        "IsRequired": true
      }
    ],
    "ReturnTypes": []
  },
  {
    "ContainingType": "API.Controllers.FacilityController",
    "Method": "EditFacility",
    "RelativePath": "api/Facility/edit-facility",
    "HttpMethod": "PUT",
    "IsController": true,
    "Order": 0,
    "Parameters": [
      {
        "Name": "request",
        "Type": "BusinessObject.DTO.UpdateFacilityDTO",
        "IsRequired": true
      }
    ],
    "ReturnTypes": []
  },
  {
    "ContainingType": "API.Controllers.FacilityController",
    "Method": "GetAll",
    "RelativePath": "api/Facility/get-all",
    "HttpMethod": "GET",
    "IsController": true,
    "Order": 0,
    "Parameters": [],
    "ReturnTypes": []
  },
  {
    "ContainingType": "API.Controllers.HomeStayController",
    "Method": "AddHomeStay",
    "RelativePath": "api/HomeStay/add-home-stay",
    "HttpMethod": "POST",
    "IsController": true,
    "Order": 0,
    "Parameters": [
      {
        "Name": "X-User-Id",
        "Type": "System.Guid",
        "IsRequired": false
      },
      {
        "Name": "request",
        "Type": "BusinessObject.DTO.AddHomeStayRequest",
        "IsRequired": true
      }
    ],
    "ReturnTypes": []
  },
  {
    "ContainingType": "API.Controllers.HomeStayController",
    "Method": "AddHomeStayAmennity",
    "RelativePath": "api/HomeStay/add-home-stay-amenity",
    "HttpMethod": "POST",
    "IsController": true,
    "Order": 0,
    "Parameters": [
      {
        "Name": "request",
        "Type": "BusinessObject.DTO.AddAmenityDTO",
        "IsRequired": true
      }
    ],
    "ReturnTypes": []
  },
  {
    "ContainingType": "API.Controllers.HomeStayController",
    "Method": "AddHomeStayImage",
    "RelativePath": "api/HomeStay/add-home-stay-image",
    "HttpMethod": "POST",
    "IsController": true,
    "Order": 0,
    "Parameters": [
      {
        "Name": "request",
        "Type": "BusinessObject.DTO.HomeStayImageDTO",
        "IsRequired": true
      }
    ],
    "ReturnTypes": []
  },
  {
    "ContainingType": "API.Controllers.HomeStayController",
    "Method": "DeleteHomeStay",
    "RelativePath": "api/HomeStay/delete-home-stay",
    "HttpMethod": "DELETE",
    "IsController": true,
    "Order": 0,
    "Parameters": [
      {
        "Name": "homeStayID",
        "Type": "System.Guid",
        "IsRequired": false
      }
    ],
    "ReturnTypes": []
  },
  {
    "ContainingType": "API.Controllers.HomeStayController",
    "Method": "DeleteHomeStayAmenity",
    "RelativePath": "api/HomeStay/delete-home-stay-amenity",
    "HttpMethod": "DELETE",
    "IsController": true,
    "Order": 0,
    "Parameters": [
      {
        "Name": "HomeStayID",
        "Type": "System.Guid",
        "IsRequired": false
      },
      {
        "Name": "AmenityID",
        "Type": "System.Guid",
        "IsRequired": false
      }
    ],
    "ReturnTypes": []
  },
  {
    "ContainingType": "API.Controllers.HomeStayController",
    "Method": "DeleteHomeStayImage",
    "RelativePath": "api/HomeStay/delete-home-stay-image",
    "HttpMethod": "DELETE",
    "IsController": true,
    "Order": 0,
    "Parameters": [
      {
        "Name": "request",
        "Type": "BusinessObject.DTO.DeleteHomeStayImageDTO",
        "IsRequired": true
      }
    ],
    "ReturnTypes": []
  },
  {
    "ContainingType": "API.Controllers.HomeStayController",
    "Method": "EditHomeStay",
    "RelativePath": "api/HomeStay/edit-home-stay-information",
    "HttpMethod": "PUT",
    "IsController": true,
    "Order": 0,
    "Parameters": [
      {
        "Name": "request",
        "Type": "BusinessObject.DTO.EditHomeStayInforRequest",
        "IsRequired": true
      }
    ],
    "ReturnTypes": []
  },
  {
    "ContainingType": "API.Controllers.HomeStayController",
    "Method": "FilterHomeStayWithStatus",
    "RelativePath": "api/HomeStay/filter-home-stay-with-status",
    "HttpMethod": "GET",
    "IsController": true,
    "Order": 0,
    "Parameters": [
      {
        "Name": "status",
        "Type": "System.Boolean",
        "IsRequired": false
      }
    ],
    "ReturnTypes": []
  },
  {
    "ContainingType": "API.Controllers.HomeStayController",
    "Method": "GetAllHomeStay",
    "RelativePath": "api/HomeStay/get-all-home-stay",
    "HttpMethod": "POST",
    "IsController": true,
    "Order": 0,
    "Parameters": [
      {
        "Name": "request",
        "Type": "BusinessObject.DTO.FilterDTO",
        "IsRequired": true
      }
    ],
    "ReturnTypes": []
  },
  {
    "ContainingType": "API.Controllers.HomeStayController",
    "Method": "GetAllCity",
    "RelativePath": "api/HomeStay/get-city-list",
    "HttpMethod": "GET",
    "IsController": true,
    "Order": 0,
    "Parameters": [],
    "ReturnTypes": []
  },
  {
    "ContainingType": "API.Controllers.HomeStayController",
    "Method": "GetHomeStayDetail",
    "RelativePath": "api/HomeStay/get-home-stay-detail",
    "HttpMethod": "GET",
    "IsController": true,
    "Order": 0,
    "Parameters": [
      {
        "Name": "homeStayID",
        "Type": "System.Guid",
        "IsRequired": false
      }
    ],
    "ReturnTypes": []
  },
  {
    "ContainingType": "API.Controllers.HomeStayController",
    "Method": "GetHomeStayImage",
    "RelativePath": "api/HomeStay/get-home-stay-image",
    "HttpMethod": "GET",
    "IsController": true,
    "Order": 0,
    "Parameters": [
      {
        "Name": "homeStayID",
        "Type": "System.Guid",
        "IsRequired": false
      }
    ],
    "ReturnTypes": []
  },
  {
    "ContainingType": "API.Controllers.HomeStayController",
    "Method": "SearchByCity",
    "RelativePath": "api/HomeStay/search-by-city",
    "HttpMethod": "GET",
    "IsController": true,
    "Order": 0,
    "Parameters": [
      {
        "Name": "city",
        "Type": "System.String",
        "IsRequired": false
      }
    ],
    "ReturnTypes": []
  },
  {
    "ContainingType": "API.Controllers.HomeStayController",
    "Method": "SearchHomeStay",
    "RelativePath": "api/HomeStay/search-home-stay",
    "HttpMethod": "GET",
    "IsController": true,
    "Order": 0,
    "Parameters": [
      {
        "Name": "CheckInDate",
        "Type": "System.DateTime",
        "IsRequired": false
      },
      {
        "Name": "CheckOutDate",
        "Type": "System.DateTime",
        "IsRequired": false
      }
    ],
    "ReturnTypes": []
  },
  {
    "ContainingType": "API.Controllers.PaymentController",
    "Method": "CreatePayment",
    "RelativePath": "api/Payment",
    "HttpMethod": "POST",
    "IsController": true,
    "Order": 0,
    "Parameters": [
      {
        "Name": "bookingID",
        "Type": "System.Guid",
        "IsRequired": false
      }
    ],
    "ReturnTypes": []
  },
  {
    "ContainingType": "API.Controllers.PaymentController",
    "Method": "PaymentReturn",
    "RelativePath": "api/Payment/payment-return",
    "HttpMethod": "GET",
    "IsController": true,
    "Order": 0,
    "Parameters": [
      {
        "Name": "code",
        "Type": "System.String",
        "IsRequired": false
      },
      {
        "Name": "id",
        "Type": "System.String",
        "IsRequired": false
      },
      {
        "Name": "cancel",
        "Type": "System.String",
        "IsRequired": false
      },
      {
        "Name": "status",
        "Type": "System.String",
        "IsRequired": false
      },
      {
        "Name": "orderCode",
        "Type": "System.String",
        "IsRequired": false
      }
    ],
    "ReturnTypes": []
  },
  {
    "ContainingType": "API.Controllers.UploadController",
    "Method": "UploadImage",
    "RelativePath": "api/Upload/upload-image",
    "HttpMethod": "POST",
    "IsController": true,
    "Order": 0,
    "Parameters": [
      {
        "Name": "File",
        "Type": "Microsoft.AspNetCore.Http.IFormFile",
        "IsRequired": false
      }
    ],
    "ReturnTypes": []
  },
  {
    "ContainingType": "API.Controllers.UserController",
    "Method": "GetAll",
    "RelativePath": "api/User",
    "HttpMethod": "GET",
    "IsController": true,
    "Order": 0,
    "Parameters": [
      {
        "Name": "pageNumber",
        "Type": "System.Int32",
        "IsRequired": false
      },
      {
        "Name": "pageSize",
        "Type": "System.Int32",
        "IsRequired": false
      }
    ],
    "ReturnTypes": []
  },
  {
    "ContainingType": "API.Controllers.UserController",
    "Method": "Get",
    "RelativePath": "api/User/{id}",
    "HttpMethod": "GET",
    "IsController": true,
    "Order": 0,
    "Parameters": [
      {
        "Name": "id",
        "Type": "System.Guid",
        "IsRequired": true
      }
    ],
    "ReturnTypes": []
  },
  {
    "ContainingType": "API.Controllers.UserController",
    "Method": "Update",
    "RelativePath": "api/User/{id}",
    "HttpMethod": "PUT",
    "IsController": true,
    "Order": 0,
    "Parameters": [
      {
        "Name": "id",
        "Type": "System.Guid",
        "IsRequired": true
      },
      {
        "Name": "request",
        "Type": "BusinessObject.DTO.UpdateUserDTO",
        "IsRequired": true
      }
    ],
    "ReturnTypes": []
  },
  {
    "ContainingType": "API.Controllers.VoucherController",
    "Method": "CreateVoucher",
    "RelativePath": "api/Voucher/create-voucher",
    "HttpMethod": "POST",
    "IsController": true,
    "Order": 0,
    "Parameters": [
      {
        "Name": "voucher",
        "Type": "BusinessObject.Entities.Voucher",
        "IsRequired": true
      }
    ],
    "ReturnTypes": []
  },
  {
    "ContainingType": "API.Controllers.VoucherController",
    "Method": "EditVoucher",
    "RelativePath": "api/Voucher/edit-voucher/{id}",
    "HttpMethod": "PUT",
    "IsController": true,
    "Order": 0,
    "Parameters": [
      {
        "Name": "id",
        "Type": "System.Guid",
        "IsRequired": true
      },
      {
        "Name": "voucherDto",
        "Type": "BusinessObject.DTO.EditVoucherDTO",
        "IsRequired": true
      }
    ],
    "ReturnTypes": []
  },
  {
    "ContainingType": "API.Controllers.VoucherController",
    "Method": "GetVouchers",
    "RelativePath": "api/Voucher/list",
    "HttpMethod": "GET",
    "IsController": true,
    "Order": 0,
    "Parameters": [
      {
        "Name": "onlyValid",
        "Type": "System.Boolean",
        "IsRequired": false
      }
    ],
    "ReturnTypes": []
  },
  {
    "ContainingType": "API.Controllers.VoucherController",
    "Method": "ReceiveVoucher",
    "RelativePath": "api/Voucher/receive",
    "HttpMethod": "POST",
    "IsController": true,
    "Order": 0,
    "Parameters": [
      {
        "Name": "request",
        "Type": "BusinessObject.DTO.ReceiveVoucherRequest",
        "IsRequired": true
      }
    ],
    "ReturnTypes": []
  },
  {
    "ContainingType": "API.Controllers.VoucherController",
    "Method": "GetUserVouchers",
    "RelativePath": "api/Voucher/user-vouchers",
    "HttpMethod": "GET",
    "IsController": true,
    "Order": 0,
    "Parameters": [
      {
        "Name": "X-User-Id",
        "Type": "System.Guid",
        "IsRequired": false
      }
    ],
    "ReturnTypes": []
  }
]